pyrappel/__init__.py
pyrappel/asm.py
pyrappel/cli.py
pyrappel/config.py
pyrappel/elf.py
pyrappel/exec_file.py
pyrappel/ptrace.py
pyrappel/types.py
pyrappel/ui.py
pyrappel/utils.py
pyrappel/arch/__init__.py
pyrappel/arch/strategy.py
pyrappel-0.1.0.dist-info/METADATA
pyrappel-0.1.0.dist-info/WHEEL
pyrappel-0.1.0.dist-info/entry_points.txt
pyrappel-0.1.0.dist-info/RECORD
