Metadata-Version: 2.4
Name: pyrappel
Version: 0.1.0
Summary: Interactive assembler with ptrace - Python version of rappel
Project-URL: Homepage, https://github.com/yrp604/rappel
Project-URL: Repository, https://github.com/yrp604/rappel
Project-URL: Issues, https://github.com/yrp604/rappel/issues
Author: PyRappel Contributors
Maintainer: PyRappel Contributors
License: MIT
Keywords: assembler,binary-analysis,ptrace,reverse-engineering,security
Classifier: Development Status :: 4 - Beta
Classifier: Intended Audience :: Developers
Classifier: Intended Audience :: Information Technology
Classifier: License :: OSI Approved :: MIT License
Classifier: Operating System :: POSIX :: Linux
Classifier: Programming Language :: Python :: 3
Classifier: Programming Language :: Python :: 3.11
Classifier: Programming Language :: Python :: 3.12
Classifier: Topic :: Security
Classifier: Topic :: Software Development :: Assemblers
Classifier: Topic :: Software Development :: Debuggers
Requires-Python: >=3.11
Requires-Dist: keystone-engine>=0.9.2
Requires-Dist: pwntools>=4.14.1
Requires-Dist: python-ptrace>=0.9.9
Provides-Extra: dev
Requires-Dist: black>=22.0.0; extra == 'dev'
Requires-Dist: flake8>=4.0.0; extra == 'dev'
Requires-Dist: pytest>=7.0.0; extra == 'dev'
